AUTHORS
LICENSE
MANIFEST.in
README.md
setup.py
cqlengine/VERSION
cqlengine/__init__.py
cqlengine/columns.py
cqlengine/connection.py
cqlengine/exceptions.py
cqlengine/functions.py
cqlengine/management.py
cqlengine/models.py
cqlengine/named.py
cqlengine/operators.py
cqlengine/query.py
cqlengine/statements.py
cqlengine.egg-info/PKG-INFO
cqlengine.egg-info/SOURCES.txt
cqlengine.egg-info/dependency_links.txt
cqlengine.egg-info/requires.txt
cqlengine.egg-info/top_level.txt
cqlengine/tests/__init__.py
cqlengine/tests/base.py
cqlengine/tests/test_batch_query.py
cqlengine/tests/test_consistency.py
cqlengine/tests/test_ifnotexists.py
cqlengine/tests/test_load.py
cqlengine/tests/test_timestamp.py
cqlengine/tests/test_ttl.py
cqlengine/tests/columns/__init__.py
cqlengine/tests/columns/test_container_columns.py
cqlengine/tests/columns/test_counter_column.py
cqlengine/tests/columns/test_static_column.py
cqlengine/tests/columns/test_validation.py
cqlengine/tests/columns/test_value_io.py
cqlengine/tests/connections/__init__.py
cqlengine/tests/management/__init__.py
cqlengine/tests/management/test_compaction_settings.py
cqlengine/tests/management/test_management.py
cqlengine/tests/model/__init__.py
cqlengine/tests/model/test_class_construction.py
cqlengine/tests/model/test_equality_operations.py
cqlengine/tests/model/test_model.py
cqlengine/tests/model/test_model_io.py
cqlengine/tests/model/test_polymorphism.py
cqlengine/tests/model/test_updates.py
cqlengine/tests/model/test_validation.py
cqlengine/tests/model/test_value_lists.py
cqlengine/tests/operators/__init__.py
cqlengine/tests/operators/test_assignment_operators.py
cqlengine/tests/operators/test_base_operator.py
cqlengine/tests/operators/test_where_operators.py
cqlengine/tests/query/__init__.py
cqlengine/tests/query/test_batch_query.py
cqlengine/tests/query/test_datetime_queries.py
cqlengine/tests/query/test_named.py
cqlengine/tests/query/test_queryoperators.py
cqlengine/tests/query/test_queryset.py
cqlengine/tests/query/test_updates.py
cqlengine/tests/statements/__init__.py
cqlengine/tests/statements/test_assignment_clauses.py
cqlengine/tests/statements/test_assignment_statement.py
