Metadata-Version: 1.1
Name: cqlengine
Version: 0.19.0
Summary: Cassandra CQL 3 Object Mapper for Python
Home-page: https://github.com/cqlengine/cqlengine
Author: Blake Eggleston, Jon Haddad
Author-email: bdeggleston@gmail.com, jon@jonhaddad.com
License: BSD
Keywords: cassandra,cql,orm
Platform: UNKNOWN
Classifier: Environment :: Web Environment
Classifier: Environment :: Plugins
Classifier: License :: OSI Approved :: BSD License
Classifier: Operating System :: OS Independent
Classifier: Programming Language :: Python :: 2.7
Classifier: Topic :: Internet :: WWW/HTTP
Classifier: Topic :: Software Development :: Libraries :: Python Modules
